tseriesbuilding/__init__.py
tseriesbuilding/generator.py
tseriesbuilding-0.1.0.dist-info/licenses/LICENSE
tseriesbuilding-0.1.0.dist-info/WHEEL
tseriesbuilding-0.1.0.dist-info/METADATA
tseriesbuilding-0.1.0.dist-info/RECORD
