Metadata-Version: 2.4
Name: tseriesbuilding
Version: 0.1.0
Summary: Generate time series for Building applications
Author-email: Tessa Hubert <tessa_hubert@hotmail.fr>
Maintainer-email: Tessa Hubert <tessa_hubert@hotmail.fr>
Requires-Python: >=3.10
Classifier: Development Status :: 4 - Beta
Classifier: Intended Audience :: Developers
Classifier: License :: OSI Approved :: BSD License
Classifier: Programming Language :: Python :: 3
Classifier: Programming Language :: Python :: 3.10
Classifier: Programming Language :: Python :: 3.11
Classifier: Programming Language :: Python :: 3.12
Classifier: Programming Language :: Python :: 3.13
License-File: LICENSE
Requires-Dist: numpy>=1.22.4, <2.0
Requires-Dist: pandas>=2.0.0, <3.0
Requires-Dist: pytest>=7.0.0 ; extra == "dev"
Requires-Dist: pre-commit>=3.3.3 ; extra == "dev"
Project-URL: Source, https://github.com/BuildingEnergySimulationTools/tseriesbuilding
Provides-Extra: dev
